whatsapp_api_client_python/API.py
whatsapp_api_client_python/__init__.py
whatsapp_api_client_python/response.py
whatsapp_api_client_python/tools/__init__.py
whatsapp_api_client_python/tools/account.py
whatsapp_api_client_python/tools/device.py
whatsapp_api_client_python/tools/groups.py
whatsapp_api_client_python/tools/journals.py
whatsapp_api_client_python/tools/marking.py
whatsapp_api_client_python/tools/partner.py
whatsapp_api_client_python/tools/queues.py
whatsapp_api_client_python/tools/receiving.py
whatsapp_api_client_python/tools/sending.py
whatsapp_api_client_python/tools/serviceMethods.py
whatsapp_api_client_python/tools/statuses.py
whatsapp_api_client_python/tools/webhooks.py
whatsapp_api_client_python-0.0.53.dist-info/licenses/LICENSE
whatsapp_api_client_python-0.0.53.dist-info/METADATA
whatsapp_api_client_python-0.0.53.dist-info/WHEEL
whatsapp_api_client_python-0.0.53.dist-info/top_level.txt
whatsapp_api_client_python-0.0.53.dist-info/RECORD
